gh_parser/__init__.py
gh_parser/__main__.py
gh_parser/gh_parser.py
gh_parser/utils/__init__.py
gh_parser/utils/cli.py
gh_parser/utils/endpoints.py
gh_parser/utils/exceptions.py
gh_parser/utils/parsers.py
gh_parser/utils/type_hints.py
gh_parser/utils/utils.py
gh_parser/utils/wrappers.py
gh_parser-1.0.3.dist-info/LICENSE.md
gh_parser-1.0.3.dist-info/METADATA
gh_parser-1.0.3.dist-info/WHEEL
gh_parser-1.0.3.dist-info/entry_points.txt
gh_parser-1.0.3.dist-info/top_level.txt
gh_parser-1.0.3.dist-info/RECORD
