Metadata-Version: 2.2
Name: gh_parser
Version: 1.0.3
Summary: A package for parsing GitHub API.
Home-page: https://github.com/yousefabuz17/GitHubParser
Download-URL: https://github.com/yousefabuz17/GitHubParser.git
Author: Yousef Abuzahrieh
Author-email: yousefzahrieh17@gmail.com
License: Apache Software License
Platform: Windows
Platform: Linux
Platform: MacOS
Classifier: Development Status :: 4 - Beta
Classifier: Intended Audience :: Developers
Classifier: License :: OSI Approved :: Apache Software License
Classifier: Operating System :: OS Independent
Classifier: Programming Language :: Python :: 3
Classifier: Programming Language :: Python :: 3 :: Only
Classifier: Topic :: Utilities
License-File: LICENSE.md
Dynamic: download-url
